exebuild/__init__.py
exebuild/__main__.py
exebuild/tests/smallexe64.exe
exebuild/tests/smallexe64_installer.exe
exebuild/tests/test.nsi
exebuild/tests/test_exebuild.py
exebuild-0.1.1.dist-info/LICENSE
exebuild-0.1.1.dist-info/METADATA
exebuild-0.1.1.dist-info/WHEEL
exebuild-0.1.1.dist-info/entry_points.txt
exebuild-0.1.1.dist-info/top_level.txt
exebuild-0.1.1.dist-info/RECORD
