Metadata-Version: 2.1
Name: exebuild
Version: 0.1.1
Summary: Azure Code signing tool for Windows executable.
Author-email: Patrik Dufresne <patrik@ikus-soft.com>
License: MIT License
Project-URL: Homepage, https://gitlab.com/ikus-soft/exebuild
Classifier: Development Status :: 4 - Beta
Classifier: License :: OSI Approved :: MIT License
Classifier: Programming Language :: Python :: 3.6
Classifier: Programming Language :: Python :: 3.7
Classifier: Programming Language :: Python :: 3.8
Classifier: Programming Language :: Python :: 3.9
Classifier: Programming Language :: Python :: 3.10
Requires-Python: <4,>=3.6
License-File: LICENSE
Requires-Dist: requests
Provides-Extra: test
